e621py_wrapper/__init__.py
e621py_wrapper/e621_endpoints.py
e621py_wrapper/e621_wrapper.py
e621py_wrapper-0.1.10.dist-info/LICENSE
e621py_wrapper-0.1.10.dist-info/METADATA
e621py_wrapper-0.1.10.dist-info/WHEEL
e621py_wrapper-0.1.10.dist-info/top_level.txt
e621py_wrapper-0.1.10.dist-info/RECORD
