Metadata-Version: 2.1
Name: e621py-wrapper
Version: 0.1.10
Summary: A well featured wrapper for e621.net
Home-page: https://github.com/tracer755/e621-wrappers
Author: Tracer755
Author-email: jason@klasstek.com
Project-URL: Bug Tracker, https://github.com/tracer755/e621-wrappers/issues
Classifier: Programming Language :: Python :: 3
Classifier: License :: OSI Approved :: MIT License
Classifier: Operating System :: OS Independent
Requires-Python: >=3.6
License-File: LICENSE
